enoslib/__init__.py
enoslib/api.py
enoslib/collections.py
enoslib/config.py
enoslib/constants.py
enoslib/docker.py
enoslib/enos_inventory.py
enoslib/errors.py
enoslib/local.py
enoslib/log.py
enoslib/objects.py
enoslib/task.py
enoslib/utils.py
enoslib/version.py
enoslib/version.txt
enoslib/ansible/utils.yml
enoslib/ansible/roles/utils/tasks/check_network.yml
enoslib/ansible/roles/utils/tasks/main.yml
enoslib/ansible/roles/utils/templates/facts.json.j2
enoslib/ansible/roles/utils/templates/hosts.txt.j2
enoslib/ansible/roles/utils/templates/ips.txt.j2
enoslib/html/__init__.py
enoslib/html/style.css
enoslib/infra/__init__.py
enoslib/infra/configuration.py
enoslib/infra/provider.py
enoslib/infra/providers.py
enoslib/infra/schema.py
enoslib/infra/utils.py
enoslib/infra/enos_chameleonbaremetal/__init__.py
enoslib/infra/enos_chameleonbaremetal/configuration.py
enoslib/infra/enos_chameleonbaremetal/constants.py
enoslib/infra/enos_chameleonbaremetal/provider.py
enoslib/infra/enos_chameleonedge/__init__.py
enoslib/infra/enos_chameleonedge/chameleon_api.py
enoslib/infra/enos_chameleonedge/chi_api_utils.py
enoslib/infra/enos_chameleonedge/configuration.py
enoslib/infra/enos_chameleonedge/constants.py
enoslib/infra/enos_chameleonedge/error.py
enoslib/infra/enos_chameleonedge/objects.py
enoslib/infra/enos_chameleonedge/provider.py
enoslib/infra/enos_chameleonedge/schema.py
enoslib/infra/enos_chameleonkvm/__init__.py
enoslib/infra/enos_chameleonkvm/configuration.py
enoslib/infra/enos_chameleonkvm/constants.py
enoslib/infra/enos_chameleonkvm/provider.py
enoslib/infra/enos_chameleonkvm/schema.py
enoslib/infra/enos_distem/__init__.py
enoslib/infra/enos_distem/configuration.py
enoslib/infra/enos_distem/constants.py
enoslib/infra/enos_distem/provider.py
enoslib/infra/enos_distem/schema.py
enoslib/infra/enos_fabric/__init__.py
enoslib/infra/enos_fabric/configuration.py
enoslib/infra/enos_fabric/constants.py
enoslib/infra/enos_fabric/provider.py
enoslib/infra/enos_fabric/schema.py
enoslib-10.5.0.dist-info/licenses/LICENSE.txt
enoslib-10.5.0.dist-info/METADATA
enoslib-10.5.0.dist-info/WHEEL
enoslib-10.5.0.dist-info/top_level.txt
enoslib-10.5.0.dist-info/RECORD
